swiftbot/__init__.py
swiftbot/button.py
swiftbot/client.py
swiftbot/context.py
swiftbot/filters.py
swiftbot/router.py
swiftbot/types.py
swiftbot/update_types.py
swiftbot/api/__init__.py
swiftbot/api/telegram.py
swiftbot/connection/__init__.py
swiftbot/connection/pool.py
swiftbot/connection/worker.py
swiftbot/exceptions/__init__.py
swiftbot/exceptions/api.py
swiftbot/exceptions/base.py
swiftbot/exceptions/handlers.py
swiftbot/middleware/__init__.py
swiftbot/middleware/analytics.py
swiftbot/middleware/auth.py
swiftbot/middleware/base.py
swiftbot/middleware/logger.py
swiftbot/middleware/rate_limiter.py
swiftbot/webhook/__init__.py
swiftbot/webhook/server.py
swiftbot-1.0.2.dist-info/LICENSE
swiftbot-1.0.2.dist-info/METADATA
swiftbot-1.0.2.dist-info/WHEEL
swiftbot-1.0.2.dist-info/top_level.txt
swiftbot-1.0.2.dist-info/RECORD
