Metadata-Version: 2.1
Name: swiftbot
Version: 1.0.2
Summary: Ultra-fast Telegram bot framework with 30× faster routing & consume 20-30% less memory
Home-page: https://github.com/Arjun-M/SwiftBot
Author: Arjun-M
Author-email: 
Classifier: Development Status :: 4 - Beta
Classifier: Intended Audience :: Developers
Classifier: Topic :: Software Development :: Libraries :: Python Modules
Classifier: License :: OSI Approved :: MIT License
Classifier: Programming Language :: Python :: 3
Classifier: Programming Language :: Python :: 3.10
Classifier: Programming Language :: Python :: 3.11
Classifier: Programming Language :: Python :: 3.12
Classifier: Topic :: Communications :: Chat
Classifier: Framework :: AsyncIO
Requires-Python: >=3.10
License-File: LICENSE
Requires-Dist: httpx<0.28.0,>=0.27.0
Requires-Dist: httpx[http2]<0.28.0,>=0.27.0
Requires-Dist: aiohttp==3.13.2
Provides-Extra: dev
Requires-Dist: pytest<8.0.0,>=7.4.0; extra == "dev"
Requires-Dist: pytest-asyncio<0.22.0,>=0.21.0; extra == "dev"
Provides-Extra: webhook
Requires-Dist: uvicorn<0.26.0,>=0.23.0; extra == "webhook"
